weighted_buzzwords/__init__.py
weighted_buzzwords/valuedbuzzwords.py
weighted_buzzwords-0.1.0.dist-info/WHEEL
weighted_buzzwords-0.1.0.dist-info/entry_points.txt
weighted_buzzwords-0.1.0.dist-info/METADATA
weighted_buzzwords-0.1.0.dist-info/RECORD
