Metadata-Version: 2.3
Name: weighted-buzzwords
Version: 0.1.0
Summary: Add your description here
Author: jonathan graf
Author-email: jonathan graf <jonathangraf@outlook.de>
Requires-Dist: jupyter>=1.1.1
Requires-Dist: matplotlib
Requires-Dist: squarify>=0.4.4
Requires-Python: >=3.11
